apex/__init__.py
apex/__main__.py
apex/build/__init__.py
apex/build/apex_syntax.py
apex/build/questions.py
apex/cmd/__init__.py
apex/cmd/generate.py
apex/cmd/header.py
apexx/__init__.py
apexx/__main__.py
apexx/build/__init__.py
apexx/build/apex_syntax.py
apexx/build/questions.py
apexx/cmd/__init__.py
apexx/cmd/generate.py
apexx/cmd/header.py
apexx-0.0.2.dist-info/LICENSE
apexx-0.0.2.dist-info/METADATA
apexx-0.0.2.dist-info/WHEEL
apexx-0.0.2.dist-info/entry_points.txt
apexx-0.0.2.dist-info/top_level.txt
apexx-0.0.2.dist-info/RECORD
