Metadata-Version: 2.1
Name: apexx
Version: 0.0.2
Summary: Apex-x is a project to create a new project by using a blueprint for ANY LANGUAGE!
Home-page: https://github.com/n25a/Apex
Author: Nima Mashhadi M. Reza
Author-email: n.twenty.five.a@gmail.com
Classifier: Programming Language :: Python :: 3
Classifier: License :: OSI Approved :: MIT License
Classifier: Operating System :: OS Independent
Requires-Python: >=3.7
License-File: LICENSE
Requires-Dist: asgiref ==3.8.1
Requires-Dist: certifi ==2024.6.2
Requires-Dist: charset-normalizer ==3.3.2
Requires-Dist: click ==8.1.7
Requires-Dist: Django ==4.2.13
Requires-Dist: django-emoji ==2.2.2
Requires-Dist: emoji ==2.12.1
Requires-Dist: idna ==3.7
Requires-Dist: markdown-it-py ==3.0.0
Requires-Dist: mdurl ==0.1.2
Requires-Dist: Pygments ==2.18.0
Requires-Dist: requests ==2.32.3
Requires-Dist: rich ==13.7.1
Requires-Dist: shellingham ==1.5.4
Requires-Dist: sqlparse ==0.5.0
Requires-Dist: tqdm ==4.66.4
Requires-Dist: typer ==0.12.3
Requires-Dist: typing-extensions ==4.12.2
Requires-Dist: urllib3 ==2.2.2
